udalmap/__init__.py
udalmap/base.py
udalmap/utils.py
udalmap-0.1.3.dist-info/licenses/LICENSE
udalmap-0.1.3.dist-info/METADATA
udalmap-0.1.3.dist-info/WHEEL
udalmap-0.1.3.dist-info/top_level.txt
udalmap-0.1.3.dist-info/RECORD
